arcor2_kinali/VERSION
arcor2_kinali/__init__.py
arcor2_kinali/py.typed
arcor2_kinali/data/aubo/aubo_i5.urdf
arcor2_kinali/data/aubo/aubo_i5/meshes/collision/base_link.STL
arcor2_kinali/data/aubo/aubo_i5/meshes/collision/foreArm_Link.STL
arcor2_kinali/data/aubo/aubo_i5/meshes/collision/pedestal.STL
arcor2_kinali/data/aubo/aubo_i5/meshes/collision/shoulder_Link.STL
arcor2_kinali/data/aubo/aubo_i5/meshes/collision/upperArm_Link.STL
arcor2_kinali/data/aubo/aubo_i5/meshes/collision/wrist1_Link.STL
arcor2_kinali/data/aubo/aubo_i5/meshes/collision/wrist2_Link.STL
arcor2_kinali/data/aubo/aubo_i5/meshes/collision/wrist3_Link.STL
arcor2_kinali/data/aubo/aubo_i5/meshes/visual/base_link.DAE
arcor2_kinali/data/aubo/aubo_i5/meshes/visual/foreArm_Link.DAE
arcor2_kinali/data/aubo/aubo_i5/meshes/visual/shoulder_Link.DAE
arcor2_kinali/data/aubo/aubo_i5/meshes/visual/upperArm_Link.DAE
arcor2_kinali/data/aubo/aubo_i5/meshes/visual/wrist1_Link.DAE
arcor2_kinali/data/aubo/aubo_i5/meshes/visual/wrist2_Link.DAE
arcor2_kinali/data/aubo/aubo_i5/meshes/visual/wrist3_Link.DAE
arcor2_kinali/object_types/__init__.py
arcor2_kinali/object_types/abstract_robot.py
arcor2_kinali/object_types/abstract_simple.py
arcor2_kinali/object_types/abstract_with_pose.py
arcor2_kinali/object_types/aubo.py
arcor2_kinali/object_types/barcode.py
arcor2_kinali/object_types/ict.py
arcor2_kinali/object_types/interaction.py
arcor2_kinali/object_types/search.py
arcor2_kinali/object_types/simatic.py
arcor2_kinali/object_types/statistic.py
arcor2_kinali/scripts/__init__.py
arcor2_kinali/scripts/upload_objects.py
arcor2_kinali-0.15.0.dist-info/METADATA
arcor2_kinali-0.15.0.dist-info/WHEEL
arcor2_kinali-0.15.0.dist-info/entry_points.txt
arcor2_kinali-0.15.0.dist-info/namespace_packages.txt
arcor2_kinali-0.15.0.dist-info/top_level.txt
arcor2_kinali-0.15.0.dist-info/RECORD
