Metadata-Version: 2.1
Name: arcor2-kinali
Version: 0.15.0
Summary: ARCOR2 integration for Kinali services.
Home-page: UNKNOWN
Author: Robo@FIT
Author-email: imaterna@fit.vut.cz
License: LGPL
Platform: UNKNOWN
Classifier: Development Status :: 3 - Alpha
Classifier: Intended Audience :: Developers
Classifier: Topic :: Software Development :: Build Tools
Classifier: License :: OSI Approved :: GNU Lesser General Public License v3 (LGPLv3)
Classifier: Programming Language :: Python :: 3.8
Classifier: Natural Language :: English
Classifier: Topic :: Scientific/Engineering
Requires-Python: ==3.8.*
Requires-Dist: Pillow (==8.3.1)
Requires-Dist: arcor2 (~=0.19.0)
Requires-Dist: dataclasses-jsonschema[apispec,fast-validation] (==2.14.1)
